MANIFEST.in
README.txt
setup.cfg
setup.py
archetypes/.DS_Store
archetypes/__init__.py
archetypes.multifile.egg-info/PKG-INFO
archetypes.multifile.egg-info/SOURCES.txt
archetypes.multifile.egg-info/dependency_links.txt
archetypes.multifile.egg-info/entry_points.txt
archetypes.multifile.egg-info/namespace_packages.txt
archetypes.multifile.egg-info/not-zip-safe
archetypes.multifile.egg-info/paster_plugins.txt
archetypes.multifile.egg-info/requires.txt
archetypes.multifile.egg-info/top_level.txt
archetypes/multifile/.DS_Store
archetypes/multifile/MultiFileField.py
archetypes/multifile/MultiFileWidget.py
archetypes/multifile/__init__.py
archetypes/multifile/config.py
archetypes/multifile/configure.zcml
archetypes/multifile/usei18ndude.sh
archetypes/multifile/locales/.DS_Store
archetypes/multifile/locales/archetypes.multifile.pot
archetypes/multifile/locales/manual.pot
archetypes/multifile/locales/cs/.DS_Store
archetypes/multifile/locales/cs/LC_MESSAGES/archetypes.multifile.mo
archetypes/multifile/locales/cs/LC_MESSAGES/archetypes.multifile.po
archetypes/multifile/locales/da/LC_MESSAGES/archetypes.multifile.mo
archetypes/multifile/locales/da/LC_MESSAGES/archetypes.multifile.po
archetypes/multifile/locales/en/LC_MESSAGES/archetypes.multifile.mo
archetypes/multifile/locales/en/LC_MESSAGES/archetypes.multifile.po
archetypes/multifile/locales/fr/LC_MESSAGES/archetypes.multifile.po
archetypes/multifile/locales/pt_BR/LC_MESSAGES/archetypes.multifile.po
archetypes/multifile/profiles/default/metadata.xml
archetypes/multifile/profiles/default/skins.xml
archetypes/multifile/skins/archetypes.multifile/at_multi_download.py
archetypes/multifile/skins/archetypes.multifile/multifile.css
archetypes/multifile/skins/archetypes.multifile/multifile.js
archetypes/multifile/skins/archetypes.multifile/paperclip.gif
archetypes/multifile/skins/archetypes.multifile/widget_multifile.pt
archetypes/multifile/tests/__init__.py
docs/HISTORY.txt
docs/INSTALL.txt
docs/LICENSE.GPL
docs/LICENSE.txt