Metadata-Version: 1.0
Name: archetypes.multifile
Version: 1.5
Summary: This package adds a field to upload multiple files
Home-page: http://pypi.python.org/pypi/collective.multifile
Author: Matous Hora
Author-email: matous.hora@dms4u.cz
License: GPL
Keywords: plone archetypes multi file field
Platform: UNKNOWN
Classifier: Framework :: Plone
Classifier: Programming Language :: Python
Classifier: Topic :: Software Development :: Libraries :: Python Modules
